sddns/__init__.py
sddns-2.0.0rc2.dist-info/LICENSE
sddns-2.0.0rc2.dist-info/WHEEL
sddns-2.0.0rc2.dist-info/METADATA
sddns-2.0.0rc2.dist-info/RECORD
